pyimagecuda/__init__.py
pyimagecuda/adjust.py
pyimagecuda/blend.py
pyimagecuda/effect.py
pyimagecuda/fill.py
pyimagecuda/filter.py
pyimagecuda/gl_interop.py
pyimagecuda/image.py
pyimagecuda/io.py
pyimagecuda/pyimagecuda_internal.cp312-win_amd64.pyd
pyimagecuda/resize.py
pyimagecuda/text.py
pyimagecuda/transform.py
pyimagecuda-0.1.4.dist-info/METADATA
pyimagecuda-0.1.4.dist-info/WHEEL
pyimagecuda-0.1.4.dist-info/licenses/LICENSE
pyimagecuda-0.1.4.dist-info/RECORD
