Metadata-Version: 2.2
Name: pyimagecuda
Version: 0.1.4
Summary: GPU-accelerated image processing library for Python
Author: Beltrán Offerrall
Requires-Python: >=3.10
Requires-Dist: pyvips[binary]
